secure_upload/__init__.py
secure_upload/main.py
secure_upload-0.0.1.data/scripts/secure-upload-server
secure_upload-0.0.1.dist-info/LICENSE
secure_upload-0.0.1.dist-info/METADATA
secure_upload-0.0.1.dist-info/WHEEL
secure_upload-0.0.1.dist-info/top_level.txt
secure_upload-0.0.1.dist-info/RECORD
