Metadata-Version: 2.1
Name: secure-upload
Version: 0.0.1
Summary: HTTP server for secure file uploads
Home-page: https://github.com/six-two/python-secure-upload
Author: six-two
Author-email: pip@six-two.dev
License: MIT License
Classifier: License :: OSI Approved :: MIT License
Classifier: Operating System :: POSIX :: Linux
Classifier: Programming Language :: Python :: 3
Classifier: Programming Language :: Python :: 3.9
Classifier: Programming Language :: Python :: 3.10
Requires-Python: >=3.9
License-File: LICENSE
